setup.py
Gaussbinomial/Binomialdistribution.py
Gaussbinomial/Gaussiandistribution.py
Gaussbinomial/Generaldistribution.py
Gaussbinomial/__init__.py
gbdis.egg-info/PKG-INFO
gbdis.egg-info/SOURCES.txt
gbdis.egg-info/dependency_links.txt
gbdis.egg-info/not-zip-safe
gbdis.egg-info/top_level.txt